treetops/__init__.py
treetops/example.py
treetops-0.0.3.dist-info/licenses/LICENSE
treetops-0.0.3.dist-info/METADATA
treetops-0.0.3.dist-info/WHEEL
treetops-0.0.3.dist-info/top_level.txt
treetops-0.0.3.dist-info/RECORD
