Metadata-Version: 2.4
Name: treetops
Version: 0.0.3
Summary: A simple Python package template
Author-email: Your Name <your.email@example.com>
License: MIT
Project-URL: Homepage, https://github.com/tylerlanigan/treetops
Project-URL: Documentation, https://github.com/tylerlanigan/treetops#readme
Project-URL: Repository, https://github.com/tylerlanigan/treetops
Project-URL: Issues, https://github.com/tylerlanigan/treetops/issues
Keywords: template,package
Classifier: Development Status :: 3 - Alpha
Classifier: Intended Audience :: Developers
Classifier: License :: OSI Approved :: MIT License
Classifier: Programming Language :: Python :: 3
Classifier: Programming Language :: Python :: 3.8
Classifier: Programming Language :: Python :: 3.9
Classifier: Programming Language :: Python :: 3.10
Classifier: Programming Language :: Python :: 3.11
Classifier: Programming Language :: Python :: 3.12
Requires-Python: >=3.8
License-File: LICENSE
Provides-Extra: dev
Requires-Dist: pytest>=7.0.0; extra == "dev"
Dynamic: license-file
